pywesaspinall/Tools.py
pywesaspinall/__init__.py
pywesaspinall-0.1.0.dist-info/METADATA
pywesaspinall-0.1.0.dist-info/WHEEL
pywesaspinall-0.1.0.dist-info/RECORD
