Metadata-Version: 2.1
Name: pywesaspinall
Version: 0.1.0
Summary: A package for Wes Aspinall.
License: MIT
Author: Wes Aspinall
Requires-Python: >=3.9,<4.0
Classifier: License :: OSI Approved :: MIT License
Classifier: Programming Language :: Python :: 3
Classifier: Programming Language :: Python :: 3.9
Classifier: Programming Language :: Python :: 3.10
Classifier: Programming Language :: Python :: 3.11
Classifier: Programming Language :: Python :: 3.12
Requires-Dist: backports-tarfile (==1.2.0)
Requires-Dist: build (==1.2.1)
Requires-Dist: certifi (==2024.7.4)
Requires-Dist: charset-normalizer (==3.3.2)
Requires-Dist: docutils (==0.21.2)
Requires-Dist: idna (==3.7)
Requires-Dist: importlib-metadata (==8.2.0)
Requires-Dist: jaraco-classes (==3.4.0)
Requires-Dist: jaraco-context (==5.3.0)
Requires-Dist: jaraco-functools (==4.0.2)
Requires-Dist: keyring (==25.3.0)
Requires-Dist: markdown-it-py (==3.0.0)
Requires-Dist: mdurl (==0.1.2)
Requires-Dist: more-itertools (==10.3.0)
Requires-Dist: nh3 (==0.2.18)
Requires-Dist: packaging (==24.1)
Requires-Dist: pkginfo (==1.10.0)
Requires-Dist: pygments (==2.18.0)
Requires-Dist: pyproject-hooks (==1.1.0)
Requires-Dist: readme-renderer (==44.0)
Requires-Dist: requests (==2.32.3)
Requires-Dist: requests-toolbelt (==1.0.0)
Requires-Dist: rfc3986 (==2.0.0)
Requires-Dist: rich (==13.7.1)
Requires-Dist: twine (==5.1.1)
Requires-Dist: urllib3 (==2.2.2)
Requires-Dist: zipp (==3.19.2)
